event_photo_gallery/__init__.py
event_photo_gallery/admin.py
event_photo_gallery/default_settings.py
event_photo_gallery/models.py
event_photo_gallery/photos.py
event_photo_gallery/public.py
event_photo_gallery/utils.py
event_photo_gallery/static/css/style.css
event_photo_gallery/templates/admin_base.html
event_photo_gallery/templates/base.html
event_photo_gallery/templates/footer.html
event_photo_gallery/templates/header.html
event_photo_gallery/templates/pages/401.html
event_photo_gallery/templates/pages/404.html
event_photo_gallery/templates/pages/gallery.html
event_photo_gallery/templates/pages/login.html
event_photo_gallery/templates/pages/photo.html
event_photo_gallery/templates/pages/admin/categories.html
event_photo_gallery/templates/pages/admin/index.html
event_photo_gallery/templates/pages/admin/users.html
event_photo_gallery-1.0.2.dist-info/LICENSE
event_photo_gallery-1.0.2.dist-info/METADATA
event_photo_gallery-1.0.2.dist-info/WHEEL
event_photo_gallery-1.0.2.dist-info/top_level.txt
event_photo_gallery-1.0.2.dist-info/RECORD
